bp_config/__init__.py
bp_config-0.1.2.dist-info/licenses/LICENSE
bp_config-0.1.2.dist-info/METADATA
bp_config-0.1.2.dist-info/WHEEL
bp_config-0.1.2.dist-info/top_level.txt
bp_config-0.1.2.dist-info/RECORD
