Metadata-Version: 2.4
Name: bp-config
Version: 0.1.2
Summary: A configuration file handler supporting YAML, JSON and TOML formats
Author-email: birds <cg626@163.com>
Classifier: Programming Language :: Python :: 3
Classifier: Operating System :: OS Independent
Requires-Python: >=3.8
License-File: LICENSE
Requires-Dist: PyYAML>=6.0
Requires-Dist: toml>=0.10.2
Dynamic: license-file
